{"name":"N4RUT0","id":1168288,"alias":["N4RUT0","MAGYAR0K"],"prefixi":["MAGYAR0K"],"location":{"state":null,"country":"Germany"},"smash":{"slug":"user/3f0fcfd4","url":"https://www.start.gg/user/3f0fcfd4"},"auth":[],"private":false,"images":[{"id":"2618220","type":"banner","url":"https://images.smash.gg/images/user/1168288/image-ee05abebb44caec4b6250d9227cd95e9.jpg","__typename":"Image"},{"id":"2618221","type":"profile","url":"https://images.smash.gg/images/user/1168288/image-82249886d5980bebdd75ff7d231b0edf.jpg","__typename":"Image"}],"tourneys":{"2017":[[],[],[]],"2018":[[],[],[]],"2019":[[],[],[]],"2020":[[],[{"data":{"main":{"wonAgainst":[{"name":"DadoDiciassette / DsChannel","seed":616}],"loss":[{"id":5841896,"name":"яσɢєя / Peti"},{"id":5747436,"name":"KirTs / Zipo"}],"lossPlacement":[129,257],"seed":409,"entity":5689327,"placement":513,"prizing":0},"sets":{"nodes":[{"createdAt":1597579015,"completedAt":1597583426,"startedAt":1597582938,"displayScore":"Messiah / N4RUT0 0 - KirTs / Zipo 2","fullRoundText":"Losers Round 3","totalGames":5,"winnerId":5747436,"wPlacement":25,"lPlacement":33,"stream":null,"phaseGroup":{"displayIdentifier":"A8","phase":{"name":"Bracket"}},"slots":[{"seed":{"placement":33,"seedNum":409},"standing":{"entrant":{"id":5689327,"name":"Messiah / N4RUT0","participants":[{"user":{"id":1168288},"player":{"id":1871412,"gamerTag":"N4RUT0"}},{"user":{"id":1167858},"player":{"id":1870892,"gamerTag":"Messia"}}]},"stats":{"score":{"value":0}}}},{"seed":{"placement":17,"seedNum":729},"standing":{"entrant":{"id":5747436,"name":"KirTs / Zipo","participants":[{"user":{"id":1049274},"player":{"id":1716764,"gamerTag":"Zipo"}},{"user":{"id":885966},"player":{"id":1418532,"gamerTag":"KirTs"}}]},"stats":{"score":{"value":2}}}}],"games":[{"winnerId":5747436,"stage":null,"selections":null},{"winnerId":5747436,"stage":null,"selections":null}]},{"createdAt":1597579015,"completedAt":1597581084,"startedAt":1597580455,"displayScore":"яσɢєя / Peti 2 - Messiah / N4RUT0 0","fullRoundText":"Winners Round 3","totalGames":5,"winnerId":5841896,"wPlacement":17,"lPlacement":33,"stream":null,"phaseGroup":{"displayIdentifier":"A8","phase":{"name":"Bracket"}},"slots":[{"seed":{"placement":9,"seedNum":1128},"standing":{"entrant":{"id":5841896,"name":"яσɢєя / Peti","participants":[{"user":{"id":902051},"player":{"id":1442622,"gamerTag":"яσɢєя"}},{"user":{"id":1235768},"player":{"id":1951868,"gamerTag":"Peti"}}]},"stats":{"score":{"value":2}}}},{"seed":{"placement":33,"seedNum":409},"standing":{"entrant":{"id":5689327,"name":"Messiah / N4RUT0","participants":[{"user":{"id":1168288},"player":{"id":1871412,"gamerTag":"N4RUT0"}},{"user":{"id":1167858},"player":{"id":1870892,"gamerTag":"Messia"}}]},"stats":{"score":{"value":0}}}}],"games":[{"winnerId":5841896,"stage":null,"selections":null},{"winnerId":5841896,"stage":null,"selections":null}]},{"createdAt":1597579015,"completedAt":1597580179,"startedAt":1597579828,"displayScore":"DQ","fullRoundText":"Winners Round 2","totalGames":5,"winnerId":5689327,"wPlacement":33,"lPlacement":65,"stream":null,"phaseGroup":{"displayIdentifier":"A8","phase":{"name":"Bracket"}},"slots":[{"seed":{"placement":33,"seedNum":409},"standing":{"entrant":{"id":5689327,"name":"Messiah / N4RUT0","participants":[{"user":{"id":1168288},"player":{"id":1871412,"gamerTag":"N4RUT0"}},{"user":{"id":1167858},"player":{"id":1870892,"gamerTag":"Messia"}}]},"stats":{"score":{"value":0}}}},{"seed":{"placement":65,"seedNum":616},"standing":{"entrant":{"id":5726383,"name":"DadoDiciassette / DsChannel","participants":[{"user":{"id":176606},"player":{"id":272603,"gamerTag":"DadoDiciassette"}},{"user":{"id":284744},"player":{"id":410538,"gamerTag":"DsChannel"}}]},"stats":{"score":{"value":-1}}}}],"games":null}]}},"tourney_id":495652,"tourney_name":"N4RUT0","type":0,"team":{"teamname":"Messiah / N4RUT0","teammate":{"id":1167858,"private":false,"name":"Messia","user":{"smash_id":1167858,"images":[{"id":"2754061","type":"profile","url":"https://images.smash.gg/images/user/1167858/image-302b2c44d85ce00ddd77294a25489711.jpg","__typename":"Image"},{"id":"2754064","type":"banner","url":"https://images.smash.gg/images/user/1167858/image-2bb790922a53029fc9a7d7764a6e332c.jpg","__typename":"Image"}],"url":"https://www.start.gg/user/ec54e684","playerSlug":"user/ec54e684"}}}},{"data":{"main":{"wonAgainst":[{"name":"Cindo67 / Murox67","seed":497},{"name":"mido / BTATES","seed":849}],"loss":[{"id":5451475,"name":"DARK_PHENIX93 / MASCOU"},{"id":5500591,"name":"Lian / Yohji"}],"lossPlacement":[257,129],"seed":176,"entity":5381297,"placement":385,"prizing":null},"sets":{"nodes":[{"createdAt":1593345208,"completedAt":1593351380,"startedAt":1593350616,"displayScore":"Messiah / V3n0m 0 - Lian / Yohji 2","fullRoundText":"Losers Round 3","totalGames":5,"winnerId":5500591,"wPlacement":17,"lPlacement":25,"stream":null,"phaseGroup":{"displayIdentifier":"E16","phase":{"name":"Bracket"}},"slots":[{"seed":{"placement":25,"seedNum":176},"standing":{"entrant":{"id":5381297,"name":"Messiah / V3n0m","participants":[{"user":{"id":1167858},"player":{"id":1870892,"gamerTag":"Messia"}},{"user":{"id":1168288},"player":{"id":1871412,"gamerTag":"N4RUT0"}}]},"stats":{"score":{"value":0}}}},{"seed":{"placement":9,"seedNum":593},"standing":{"entrant":{"id":5500591,"name":"Lian / Yohji","participants":[{"user":{"id":303669},"player":{"id":435083,"gamerTag":"Lian"}},{"user":{"id":1195046},"player":{"id":1902640,"gamerTag":"Yohji"}}]},"stats":{"score":{"value":2}}}}],"games":[{"winnerId":5500591,"stage":null,"selections":null},{"winnerId":5500591,"stage":null,"selections":null}]},{"createdAt":1593345208,"completedAt":1593350477,"startedAt":1593349140,"displayScore":"Messiah / V3n0m 2 - Cindo67 / Murox67 0","fullRoundText":"Losers Round 2","totalGames":5,"winnerId":5381297,"wPlacement":25,"lPlacement":33,"stream":null,"phaseGroup":{"displayIdentifier":"E16","phase":{"name":"Bracket"}},"slots":[{"seed":{"placement":25,"seedNum":176},"standing":{"entrant":{"id":5381297,"name":"Messiah / V3n0m","participants":[{"user":{"id":1167858},"player":{"id":1870892,"gamerTag":"Messia"}},{"user":{"id":1168288},"player":{"id":1871412,"gamerTag":"N4RUT0"}}]},"stats":{"score":{"value":2}}}},{"seed":{"placement":33,"seedNum":497},"standing":{"entrant":{"id":5485091,"name":"Cindo67 / Murox67","participants":[{"user":{"id":1151788},"player":{"id":1849990,"gamerTag":"Cindo67"}},{"user":{"id":1165077},"player":{"id":1867418,"gamerTag":"Murox67"}}]},"stats":{"score":{"value":0}}}}],"games":[{"winnerId":5381297,"stage":null,"selections":null},{"winnerId":5381297,"stage":null,"selections":null}]},{"createdAt":1593345208,"completedAt":1593348018,"startedAt":1593346748,"displayScore":"Messiah / V3n0m 0 - DARK_PHENIX93 / MASCOU 2","fullRoundText":"Winners Round 2","totalGames":5,"winnerId":5451475,"wPlacement":17,"lPlacement":33,"stream":null,"phaseGroup":{"displayIdentifier":"E16","phase":{"name":"Bracket"}},"slots":[{"seed":{"placement":25,"seedNum":176},"standing":{"entrant":{"id":5381297,"name":"Messiah / V3n0m","participants":[{"user":{"id":1167858},"player":{"id":1870892,"gamerTag":"Messia"}},{"user":{"id":1168288},"player":{"id":1871412,"gamerTag":"N4RUT0"}}]},"stats":{"score":{"value":0}}}},{"seed":{"placement":17,"seedNum":337},"standing":{"entrant":{"id":5451475,"name":"DARK_PHENIX93 / MASCOU","participants":[{"user":{"id":1185134},"player":{"id":1891297,"gamerTag":"MASCOU"}},{"user":{"id":1185136},"player":{"id":1891299,"gamerTag":"Sllowzy"}}]},"stats":{"score":{"value":2}}}}],"games":[{"winnerId":5451475,"stage":null,"selections":null},{"winnerId":5451475,"stage":null,"selections":null}]},{"createdAt":1593345208,"completedAt":1593346258,"startedAt":1593345694,"displayScore":"DQ","fullRoundText":"Winners Round 1","totalGames":5,"winnerId":5381297,"wPlacement":33,"lPlacement":49,"stream":null,"phaseGroup":{"displayIdentifier":"E16","phase":{"name":"Bracket"}},"slots":[{"seed":{"placement":25,"seedNum":176},"standing":{"entrant":{"id":5381297,"name":"Messiah / V3n0m","participants":[{"user":{"id":1167858},"player":{"id":1870892,"gamerTag":"Messia"}},{"user":{"id":1168288},"player":{"id":1871412,"gamerTag":"N4RUT0"}}]},"stats":{"score":{"value":0}}}},{"seed":{"placement":33,"seedNum":849},"standing":{"entrant":{"id":5517840,"name":"mido / BTATES","participants":[{"user":{"id":1050298},"player":{"id":1718952,"gamerTag":"BTATES"}},{"user":{"id":994498},"player":{"id":1895354,"gamerTag":"mido"}}]},"stats":{"score":{"value":-1}}}}],"games":null}]}},"tourney_id":482776,"type":0,"tourney_name":"N4RUT0","team":{"teamname":"Messiah / V3n0m","teammate":{"id":1167858,"private":false,"name":"Messiah","user":{"smash_id":1167858,"images":[{"id":"2754061","type":"profile","url":"https://images.smash.gg/images/user/1167858/image-302b2c44d85ce00ddd77294a25489711.jpg","__typename":"Image"},{"id":"2754064","type":"banner","url":"https://images.smash.gg/images/user/1167858/image-2bb790922a53029fc9a7d7764a6e332c.jpg","__typename":"Image"}],"url":"https://www.start.gg/user/ec54e684","playerSlug":"user/ec54e684"}}}},{"data":{"main":{"wonAgainst":[{"name":"Neko / Mo","seed":611}],"loss":[{"id":5688919,"name":"Miki ツ / BADMAAAN"},{"id":5619873,"name":"Bocosorm / Eslampro"}],"lossPlacement":[193,769],"seed":414,"entity":5580271,"placement":1025,"prizing":0},"sets":{"nodes":[{"createdAt":1595764484,"completedAt":1595769688,"startedAt":1595769242,"displayScore":"Bocosorm / Eslampro 2 - Messiah / N4RUT0 0","fullRoundText":"Losers Round 3","totalGames":5,"winnerId":5619873,"wPlacement":25,"lPlacement":33,"stream":null,"phaseGroup":{"displayIdentifier":"M6","phase":{"name":"Bracket"}},"slots":[{"seed":{"placement":25,"seedNum":606},"standing":{"entrant":{"id":5619873,"name":"Bocosorm / Eslampro","participants":[{"user":{"id":1189051},"player":{"id":1896020,"gamerTag":"Bocosorm"}},{"user":{"id":1197979},"player":{"id":1906160,"gamerTag":"Eslampro"}}]},"stats":{"score":{"value":2}}}},{"seed":{"placement":33,"seedNum":414},"standing":{"entrant":{"id":5580271,"name":"Messiah / N4RUT0","participants":[{"user":{"id":1168288},"player":{"id":1871412,"gamerTag":"N4RUT0"}},{"user":{"id":1167858},"player":{"id":1870892,"gamerTag":"Messia"}}]},"stats":{"score":{"value":0}}}}],"games":[{"winnerId":5619873,"stage":null,"selections":null},{"winnerId":5619873,"stage":null,"selections":null}]},{"createdAt":1595764484,"completedAt":1595769046,"startedAt":1595768941,"displayScore":"Neko / Mo 0 - Messiah / N4RUT0 2","fullRoundText":"Losers Round 2","totalGames":5,"winnerId":5580271,"wPlacement":33,"lPlacement":49,"stream":null,"phaseGroup":{"displayIdentifier":"M6","phase":{"name":"Bracket"}},"slots":[{"seed":{"placement":49,"seedNum":611},"standing":{"entrant":{"id":5620488,"name":"Neko / Mo","participants":[{"user":{"id":1103027},"player":{"id":1792000,"gamerTag":"Tempest?"}},{"user":{"id":841159},"player":{"id":1340164,"gamerTag":"Mo"}}]},"stats":{"score":{"value":0}}}},{"seed":{"placement":33,"seedNum":414},"standing":{"entrant":{"id":5580271,"name":"Messiah / N4RUT0","participants":[{"user":{"id":1168288},"player":{"id":1871412,"gamerTag":"N4RUT0"}},{"user":{"id":1167858},"player":{"id":1870892,"gamerTag":"Messia"}}]},"stats":{"score":{"value":2}}}}],"games":[{"winnerId":5580271,"stage":null,"selections":null},{"winnerId":5580271,"stage":null,"selections":null}]},{"createdAt":1595764484,"completedAt":1595768552,"startedAt":1595767483,"displayScore":"Messiah / N4RUT0 0 - Miki ツ / BADMAAAN 2","fullRoundText":"Winners Round 2","totalGames":5,"winnerId":5688919,"wPlacement":33,"lPlacement":49,"stream":null,"phaseGroup":{"displayIdentifier":"M6","phase":{"name":"Bracket"}},"slots":[{"seed":{"placement":33,"seedNum":414},"standing":{"entrant":{"id":5580271,"name":"Messiah / N4RUT0","participants":[{"user":{"id":1168288},"player":{"id":1871412,"gamerTag":"N4RUT0"}},{"user":{"id":1167858},"player":{"id":1870892,"gamerTag":"Messia"}}]},"stats":{"score":{"value":0}}}},{"seed":{"placement":7,"seedNum":1635},"standing":{"entrant":{"id":5688919,"name":"Miki ツ / BADMAAAN","participants":[{"user":{"id":1236887},"player":{"id":1953211,"gamerTag":"Miki ツ"}},{"user":{"id":1236888},"player":{"id":1953212,"gamerTag":"BADMAAAN"}}]},"stats":{"score":{"value":2}}}}],"games":[{"winnerId":5688919,"stage":null,"selections":null},{"winnerId":5688919,"stage":null,"selections":null}]}]}},"tourney_id":471351,"type":0,"tourney_name":"N4RUT0","team":{"teamname":"Messiah / N4RUT0","teammate":{"id":1167858,"private":false,"name":"Messia","user":{"smash_id":1167858,"images":[{"id":"2754061","type":"profile","url":"https://images.smash.gg/images/user/1167858/image-302b2c44d85ce00ddd77294a25489711.jpg","__typename":"Image"},{"id":"2754064","type":"banner","url":"https://images.smash.gg/images/user/1167858/image-2bb790922a53029fc9a7d7764a6e332c.jpg","__typename":"Image"}],"url":"https://www.start.gg/user/ec54e684","playerSlug":"user/ec54e684"}}}}],[]],"2021":[[],[],[]],"2022":[[],[],[]]}}