{"name":"Rainn","id":1229410,"alias":["Rainn"],"prefixi":[],"location":{"state":"TX","country":"United States"},"smash":{"slug":"user/8b0c9b37","url":"https://www.start.gg/user/8b0c9b37"},"auth":[],"private":false,"images":[],"tourneys":{"2017":[[],[],[]],"2018":[[],[],[]],"2019":[[],[],[]],"2020":[[{"data":{"main":{"wonAgainst":[{"name":"Glomulus","seed":2398}],"loss":[{"id":5558948,"name":"CallMeSam"},{"id":5610681,"name":"Jaweezee"}],"lossPlacement":[2049,3073],"seed":6494,"entity":5657960,"placement":4097,"prizing":null},"sets":{"nodes":[{"createdAt":1595102658,"completedAt":1595104754,"startedAt":1595104461,"displayScore":"DQ","fullRoundText":"Losers Round 2","totalGames":5,"winnerId":5610681,"wPlacement":49,"lPlacement":65,"stream":null,"phaseGroup":{"displayIdentifier":"E3","phase":{"name":"Bracket"}},"slots":[{"seed":{"placement":49,"seedNum":3107},"standing":{"entrant":{"id":5610681,"name":"Jaweezee","participants":[{"user":{"id":1216917},"player":{"id":1930284,"gamerTag":"Jaweezee"}}]},"stats":{"score":{"value":-1}}}},{"seed":{"placement":65,"seedNum":6494},"standing":{"entrant":{"id":5657960,"name":"Rainn","participants":[{"user":{"id":1229410},"player":{"id":1944477,"gamerTag":"Rainn"}}]},"stats":{"score":{"value":-1}}}}],"games":null},{"createdAt":1595102658,"completedAt":1595104385,"startedAt":1595104035,"displayScore":"DQ","fullRoundText":"Losers Round 1","totalGames":5,"winnerId":5657960,"wPlacement":65,"lPlacement":97,"stream":null,"phaseGroup":{"displayIdentifier":"E3","phase":{"name":"Bracket"}},"slots":[{"seed":{"placement":65,"seedNum":6494},"standing":{"entrant":{"id":5657960,"name":"Rainn","participants":[{"user":{"id":1229410},"player":{"id":1944477,"gamerTag":"Rainn"}}]},"stats":{"score":{"value":-1}}}},{"seed":{"placement":97,"seedNum":2398},"standing":{"entrant":{"id":5589363,"name":"Glomulus","participants":[{"user":{"id":1212662},"player":{"id":1924846,"gamerTag":"Glomulus"}}]},"stats":{"score":{"value":-1}}}}],"games":null},{"createdAt":1595102658,"completedAt":1595103977,"startedAt":1595103381,"displayScore":"DQ","fullRoundText":"Winners Round 1","totalGames":5,"winnerId":5558948,"wPlacement":65,"lPlacement":97,"stream":null,"phaseGroup":{"displayIdentifier":"E3","phase":{"name":"Bracket"}},"slots":[{"seed":{"placement":33,"seedNum":1699},"standing":{"entrant":{"id":5558948,"name":"CallMeSam","participants":[{"user":{"id":1059285},"player":{"id":1730750,"gamerTag":"CallMeSam"}}]},"stats":{"score":{"value":-1}}}},{"seed":{"placement":65,"seedNum":6494},"standing":{"entrant":{"id":5657960,"name":"Rainn","participants":[{"user":{"id":1229410},"player":{"id":1944477,"gamerTag":"Rainn"}}]},"stats":{"score":{"value":-1}}}}],"games":null}]}},"tourney_id":471344,"tourney_name":"Rainn","type":0}],[],[]],"2021":[[],[],[]],"2022":[[],[],[]]}}