{"name":"Hunter il Redento","id":305194,"alias":["Hunter il Redento"],"prefixi":[],"location":{"state":null,"country":"Italy"},"smash":{"slug":"user/119cb393","url":"https://www.start.gg/user/119cb393"},"auth":[],"private":false,"images":[],"tourneys":{"2017":[[{"data":{"main":{"wonAgainst":[{"name":"Tunihorn","seed":136},{"name":"Starfor","seed":695},{"name":"[TD]PhantomHobo","seed":886},{"name":"thibze","seed":1096}],"loss":[{"id":874876,"name":"KoM | | Ynexo"},{"id":910544,"name":"Sedahhh"}],"lossPlacement":[97,129],"seed":1910,"entity":926939,"placement":257,"prizing":null},"sets":{"nodes":[{"createdAt":1501333725,"completedAt":1501337043,"startedAt":1501336605,"displayScore":"Sedahhh 2 - Hunter il Redento 0","fullRoundText":"Losers Round 6","totalGames":5,"winnerId":910544,"wPlacement":7,"lPlacement":9,"stream":null,"phaseGroup":{"displayIdentifier":"A8","phase":{"name":"Pools"}},"slots":[{"seed":{"placement":5,"seedNum":712},"standing":{"entrant":{"id":910544,"name":"Sedahhh","participants":[{"user":{"id":300397},"player":{"id":431077,"gamerTag":"Sedahhh"}}]},"stats":{"score":{"value":2}}}},{"seed":{"placement":9,"seedNum":1910},"standing":{"entrant":{"id":926939,"name":"Hunter il Redento","participants":[{"user":{"id":305194},"player":{"id":436849,"gamerTag":"Hunter il Redento"}}]},"stats":{"score":{"value":0}}}}],"games":[{"winnerId":910544,"stage":null,"selections":[{"selectionType":"CHARACTER","selectionValue":175,"entrant":{"name":"Sedahhh"}},{"selectionType":"CHARACTER","selectionValue":161,"entrant":{"name":"Hunter il Redento"}}]},{"winnerId":910544,"stage":null,"selections":null}]},{"createdAt":1501333725,"completedAt":1501336573,"startedAt":1501335967,"displayScore":"Hunter il Redento 2 - thibze 0","fullRoundText":"Losers Round 5","totalGames":5,"winnerId":926939,"wPlacement":9,"lPlacement":13,"stream":null,"phaseGroup":{"displayIdentifier":"A8","phase":{"name":"Pools"}},"slots":[{"seed":{"placement":9,"seedNum":1910},"standing":{"entrant":{"id":926939,"name":"Hunter il Redento","participants":[{"user":{"id":305194},"player":{"id":436849,"gamerTag":"Hunter il Redento"}}]},"stats":{"score":{"value":2}}}},{"seed":{"placement":13,"seedNum":1096},"standing":{"entrant":{"id":921243,"name":"thibze","participants":[{"user":{"id":303354},"player":{"id":434731,"gamerTag":"thibze"}}]},"stats":{"score":{"value":0}}}}],"games":[{"winnerId":926939,"stage":null,"selections":null},{"winnerId":926939,"stage":null,"selections":[{"selectionType":"CHARACTER","selectionValue":161,"entrant":{"name":"Hunter il Redento"}}]}]},{"createdAt":1501333725,"completedAt":1501335428,"startedAt":1501335183,"displayScore":"DQ","fullRoundText":"Losers Round 4","totalGames":5,"winnerId":926939,"wPlacement":13,"lPlacement":17,"stream":null,"phaseGroup":{"displayIdentifier":"A8","phase":{"name":"Pools"}},"slots":[{"seed":{"placement":9,"seedNum":1910},"standing":{"entrant":{"id":926939,"name":"Hunter il Redento","participants":[{"user":{"id":305194},"player":{"id":436849,"gamerTag":"Hunter il Redento"}}]},"stats":{"score":{"value":0}}}},{"seed":{"placement":17,"seedNum":695},"standing":{"entrant":{"id":910201,"name":"Starfor","participants":[{"user":{"id":300309},"player":{"id":430922,"gamerTag":"Starfor"}}]},"stats":{"score":{"value":-1}}}}],"games":null},{"createdAt":1501333725,"completedAt":1501334830,"startedAt":1501334505,"displayScore":"DQ","fullRoundText":"Winners Round 3","totalGames":5,"winnerId":874876,"wPlacement":9,"lPlacement":17,"stream":null,"phaseGroup":{"displayIdentifier":"A8","phase":{"name":"Pools"}},"slots":[{"seed":{"placement":9,"seedNum":1910},"standing":{"entrant":{"id":926939,"name":"Hunter il Redento","participants":[{"user":{"id":305194},"player":{"id":436849,"gamerTag":"Hunter il Redento"}}]},"stats":{"score":{"value":-1}}}},{"seed":{"placement":4,"seedNum":375},"standing":{"entrant":{"id":874876,"name":"KoM | | Ynexo","participants":[{"user":{"id":289959},"player":{"id":417924,"gamerTag":"Lap"}}]},"stats":{"score":{"value":0}}}}],"games":null},{"createdAt":1501333725,"completedAt":1501334403,"startedAt":1501334104,"displayScore":"DQ","fullRoundText":"Winners Round 2","totalGames":5,"winnerId":926939,"wPlacement":17,"lPlacement":33,"stream":null,"phaseGroup":{"displayIdentifier":"A8","phase":{"name":"Pools"}},"slots":[{"seed":{"placement":9,"seedNum":1910},"standing":{"entrant":{"id":926939,"name":"Hunter il Redento","participants":[{"user":{"id":305194},"player":{"id":436849,"gamerTag":"Hunter il Redento"}}]},"stats":{"score":{"value":0}}}},{"seed":{"placement":25,"seedNum":886},"standing":{"entrant":{"id":924432,"name":"[TD]PhantomHobo","participants":[{"user":{"id":247829},"player":{"id":363320,"gamerTag":"[TD]PhantomHobo"}}]},"stats":{"score":{"value":-1}}}}],"games":null},{"createdAt":1501333725,"completedAt":1501334044,"startedAt":1501333743,"displayScore":"DQ","fullRoundText":"Winners Round 1","totalGames":5,"winnerId":926939,"wPlacement":33,"lPlacement":49,"stream":null,"phaseGroup":{"displayIdentifier":"A8","phase":{"name":"Pools"}},"slots":[{"seed":{"placement":33,"seedNum":136},"standing":{"entrant":{"id":871605,"name":"Tunihorn","participants":[{"user":{"id":174481},"player":{"id":274987,"gamerTag":"Tunihorn"}}]},"stats":{"score":{"value":-1}}}},{"seed":{"placement":9,"seedNum":1910},"standing":{"entrant":{"id":926939,"name":"Hunter il Redento","participants":[{"user":{"id":305194},"player":{"id":436849,"gamerTag":"Hunter il Redento"}}]},"stats":{"score":{"value":0}}}}],"games":null}]}},"tourney_id":38388,"tourney_name":"Hunter il Redento","type":0}],[],[]],"2018":[[],[],[]],"2019":[[],[],[]],"2020":[[],[],[]],"2021":[[],[],[]],"2022":[[],[],[]]}}