{"name":"L.Z.U","id":584341,"alias":["L.Z.U"],"prefixi":[],"location":{"state":null,"country":null},"smash":{"slug":"user/7ba6fca6","url":"https://www.start.gg/user/7ba6fca6"},"auth":[],"private":false,"images":[],"tourneys":{"2017":[[],[],[]],"2018":[[{"data":{"main":{"wonAgainst":[{"name":"[Dr]David","seed":5},{"name":"IceStorm","seed":188}],"loss":[{"id":2189050,"name":"Manuh"},{"id":2171247,"name":"Ravens | Ravens | Puchy"}],"lossPlacement":[129,65],"seed":60,"entity":2205674,"placement":97,"prizing":null},"sets":{"nodes":[{"createdAt":1540663114,"completedAt":1540664100,"startedAt":1540663490,"displayScore":"Ravens | Ravens | Puchy 2 - L.Z.U 0","fullRoundText":"Losers Round 1","totalGames":5,"winnerId":2171247,"wPlacement":65,"lPlacement":97,"stream":null,"phaseGroup":{"displayIdentifier":"1","phase":{"name":"Top 128"}},"slots":[{"seed":{"placement":65,"seedNum":68},"standing":{"entrant":{"id":2171247,"name":"Ravens | Ravens | Puchy","participants":[{"user":{"id":440959},"player":{"id":634087,"gamerTag":"Ravens | Puchy"}}]},"stats":{"score":{"value":2}}}},{"seed":{"placement":97,"seedNum":124},"standing":{"entrant":{"id":2205674,"name":"L.Z.U","participants":[{"user":{"id":584341},"player":{"id":916432,"gamerTag":"L.Z.U"}}]},"stats":{"score":{"value":0}}}}],"games":[{"winnerId":2171247,"stage":null,"selections":[{"selectionType":"CHARACTER","selectionValue":688,"entrant":{"name":"Ravens | Ravens | Puchy"}}]},{"winnerId":2171247,"stage":null,"selections":[{"selectionType":"CHARACTER","selectionValue":166,"entrant":{"name":"L.Z.U"}}]}]},{"createdAt":1540658318,"completedAt":1540661354,"startedAt":1540661053,"displayScore":"DQ","fullRoundText":"Losers Quarter-Final","totalGames":5,"winnerId":2205674,"wPlacement":4,"lPlacement":5,"stream":null,"phaseGroup":{"displayIdentifier":"28","phase":{"name":"Bracket"}},"slots":[{"seed":{"placement":5,"seedNum":5},"standing":{"entrant":{"id":2174074,"name":"[Dr]David","participants":[{"user":{"id":236713},"player":{"id":347307,"gamerTag":"Alfajorcito"}}]},"stats":{"score":{"value":-1}}}},{"seed":{"placement":3,"seedNum":60},"standing":{"entrant":{"id":2205674,"name":"L.Z.U","participants":[{"user":{"id":584341},"player":{"id":916432,"gamerTag":"L.Z.U"}}]},"stats":{"score":{"value":0}}}}],"games":null},{"createdAt":1540658318,"completedAt":1540660536,"startedAt":1540659728,"displayScore":"IceStorm 0 - L.Z.U 2","fullRoundText":"Losers Round 2","totalGames":5,"winnerId":2205674,"wPlacement":5,"lPlacement":7,"stream":null,"phaseGroup":{"displayIdentifier":"28","phase":{"name":"Bracket"}},"slots":[{"seed":{"placement":7,"seedNum":188},"standing":{"entrant":{"id":2210768,"name":"IceStorm","participants":[{"user":{"id":585573},"player":{"id":918381,"gamerTag":"IceStorm"}}]},"stats":{"score":{"value":0}}}},{"seed":{"placement":3,"seedNum":60},"standing":{"entrant":{"id":2205674,"name":"L.Z.U","participants":[{"user":{"id":584341},"player":{"id":916432,"gamerTag":"L.Z.U"}}]},"stats":{"score":{"value":2}}}}],"games":[{"winnerId":2205674,"stage":null,"selections":[{"selectionType":"CHARACTER","selectionValue":157,"entrant":{"name":"IceStorm"}},{"selectionType":"CHARACTER","selectionValue":166,"entrant":{"name":"L.Z.U"}}]},{"winnerId":2205674,"stage":null,"selections":[{"selectionType":"CHARACTER","selectionValue":166,"entrant":{"name":"IceStorm"}},{"selectionType":"CHARACTER","selectionValue":794,"entrant":{"name":"L.Z.U"}}]}]},{"createdAt":1540658318,"completedAt":1540659679,"startedAt":1540658867,"displayScore":"L.Z.U 0 - Manuh 2","fullRoundText":"Winners Quarter-Final","totalGames":5,"winnerId":2189050,"wPlacement":5,"lPlacement":7,"stream":null,"phaseGroup":{"displayIdentifier":"28","phase":{"name":"Bracket"}},"slots":[{"seed":{"placement":3,"seedNum":60},"standing":{"entrant":{"id":2205674,"name":"L.Z.U","participants":[{"user":{"id":584341},"player":{"id":916432,"gamerTag":"L.Z.U"}}]},"stats":{"score":{"value":0}}}},{"seed":{"placement":5,"seedNum":197},"standing":{"entrant":{"id":2189050,"name":"Manuh","participants":[{"user":{"id":350267},"player":{"id":490199,"gamerTag":"Manuh"}}]},"stats":{"score":{"value":2}}}}],"games":[{"winnerId":2189050,"stage":null,"selections":[{"selectionType":"CHARACTER","selectionValue":173,"entrant":{"name":"Manuh"}}]},{"winnerId":2189050,"stage":null,"selections":[{"selectionType":"CHARACTER","selectionValue":794,"entrant":{"name":"L.Z.U"}}]}]}]}},"tourney_id":222217,"tourney_name":"L.Z.U","type":0}],[],[]],"2019":[[],[],[]],"2020":[[],[],[]],"2021":[[],[],[]],"2022":[[],[],[]]}}