{"name":"Zapp","id":763240,"alias":["Zapp"],"prefixi":[],"location":{"state":"FL","country":"United States"},"smash":{"slug":"user/ae81cd99","url":"https://www.start.gg/user/ae81cd99"},"auth":[{"platform":"TWITTER","username":"zapp133"}],"private":false,"images":[{"id":"2315077","type":"profile","url":"https://images.start.gg/images/user/763240/image-3e7c185c144bff2cbc47ae02afd2009d.jpg?ehk=GMJvzLd66703eh7VlFN4xwbYdDwbMjAnrrMRef4SY0I%3D&ehkOptimized=WaIhkV6%2BzcglEMxjQTqatrzevIadOt2TJJjQ6EoGm64%3D","__typename":"Image"},{"id":"2315078","type":"banner","url":"https://images.start.gg/images/user/763240/image-fc5dde16880b04ad59285ac06f7e0a02.png?ehk=dcPrrpZZDqAstiZdLaHOARnPQFeY0VQia5OVqS89VYA%3D&ehkOptimized=8wdn%2B8S%2F13XUjobZT7Xm2GEWJEDaQ7DGzyE7EOyXEFU%3D","__typename":"Image"}],"tourneys":{"2017":[[],[],[]],"2018":[[],[],[]],"2019":[[],[],[]],"2020":[[],[],[]],"2021":[[],[],[]],"2022":[[{"data":{"main":{"wonAgainst":[{"name":"BALZ | Mork","seed":395},{"name":"NG | MPH","seed":406},{"name":"nessquik","seed":555},{"name":"yeat | Kojer!","seed":651}],"loss":[{"id":9981944,"name":"Makken"},{"id":9964621,"name":"TOO | Ninyoi"}],"lossPlacement":[129,129],"seed":374,"entity":9767558,"placement":193,"prizing":null},"sets":{"nodes":[{"createdAt":1653605750,"completedAt":1653765122,"startedAt":1653764652,"displayScore":"Zapp 0 - TOO | Ninyoi 2","fullRoundText":"Losers Round 4","totalGames":5,"winnerId":9964621,"wPlacement":9,"lPlacement":13,"stream":null,"phaseGroup":{"displayIdentifier":"UB3","phase":{"name":"Pools"}},"slots":[{"seed":{"placement":13,"seedNum":374},"standing":{"entrant":{"id":9767558,"name":"Zapp","participants":[{"user":{"id":763240},"player":{"id":1207661,"gamerTag":"Zapp"}}]},"stats":{"score":{"value":0}}}},{"seed":{"placement":9,"seedNum":278},"standing":{"entrant":{"id":9964621,"name":"TOO | Ninyoi","participants":[{"user":{"id":759516},"player":{"id":1199541,"gamerTag":"Ninyoi"}}]},"stats":{"score":{"value":2}}}}],"games":null},{"createdAt":1653605750,"completedAt":1653763971,"startedAt":null,"displayScore":"DQ","fullRoundText":"Losers Round 3","totalGames":5,"winnerId":9767558,"wPlacement":13,"lPlacement":17,"stream":null,"phaseGroup":{"displayIdentifier":"UB3","phase":{"name":"Pools"}},"slots":[{"seed":{"placement":17,"seedNum":406},"standing":{"entrant":{"id":10101319,"name":"NG | MPH","participants":[{"user":{"id":1027434},"player":{"id":1680071,"gamerTag":"MPH"}}]},"stats":{"score":{"value":-1}}}},{"seed":{"placement":13,"seedNum":374},"standing":{"entrant":{"id":9767558,"name":"Zapp","participants":[{"user":{"id":763240},"player":{"id":1207661,"gamerTag":"Zapp"}}]},"stats":{"score":{"value":0}}}}],"games":null},{"createdAt":1653605750,"completedAt":1653763823,"startedAt":1653763320,"displayScore":"Zapp 2 - BALZ | Mork 0","fullRoundText":"Losers Round 2","totalGames":5,"winnerId":9767558,"wPlacement":17,"lPlacement":25,"stream":null,"phaseGroup":{"displayIdentifier":"UB3","phase":{"name":"Pools"}},"slots":[{"seed":{"placement":13,"seedNum":374},"standing":{"entrant":{"id":9767558,"name":"Zapp","participants":[{"user":{"id":763240},"player":{"id":1207661,"gamerTag":"Zapp"}}]},"stats":{"score":{"value":2}}}},{"seed":{"placement":25,"seedNum":395},"standing":{"entrant":{"id":9777591,"name":"BALZ | Mork","participants":[{"user":{"id":900813},"player":{"id":1440257,"gamerTag":"Mork"}}]},"stats":{"score":{"value":0}}}}],"games":null},{"createdAt":1653605750,"completedAt":1653763310,"startedAt":1653762852,"displayScore":"Zapp 2 - nessquik 0","fullRoundText":"Losers Round 1","totalGames":5,"winnerId":9767558,"wPlacement":25,"lPlacement":33,"stream":null,"phaseGroup":{"displayIdentifier":"UB3","phase":{"name":"Pools"}},"slots":[{"seed":{"placement":13,"seedNum":374},"standing":{"entrant":{"id":9767558,"name":"Zapp","participants":[{"user":{"id":763240},"player":{"id":1207661,"gamerTag":"Zapp"}}]},"stats":{"score":{"value":2}}}},{"seed":{"placement":33,"seedNum":555},"standing":{"entrant":{"id":9914848,"name":"nessquik","participants":[{"user":{"id":669325},"player":{"id":1059963,"gamerTag":"nessquik"}}]},"stats":{"score":{"value":0}}}}],"games":null},{"createdAt":1653605750,"completedAt":1653762837,"startedAt":1653762239,"displayScore":"Makken 2 - Zapp 0","fullRoundText":"Winners Round 2","totalGames":5,"winnerId":9981944,"wPlacement":17,"lPlacement":33,"stream":null,"phaseGroup":{"displayIdentifier":"UB3","phase":{"name":"Pools"}},"slots":[{"seed":{"placement":9,"seedNum":139},"standing":{"entrant":{"id":9981944,"name":"Makken","participants":[{"user":{"id":1480910},"player":{"id":2264899,"gamerTag":"Makken"}}]},"stats":{"score":{"value":2}}}},{"seed":{"placement":13,"seedNum":374},"standing":{"entrant":{"id":9767558,"name":"Zapp","participants":[{"user":{"id":763240},"player":{"id":1207661,"gamerTag":"Zapp"}}]},"stats":{"score":{"value":0}}}}],"games":null},{"createdAt":1653605750,"completedAt":1653762028,"startedAt":1653761378,"displayScore":"Zapp 2 - yeat | Kojer! 0","fullRoundText":"Winners Round 1","totalGames":5,"winnerId":9767558,"wPlacement":33,"lPlacement":33,"stream":null,"phaseGroup":{"displayIdentifier":"UB3","phase":{"name":"Pools"}},"slots":[{"seed":{"placement":13,"seedNum":374},"standing":{"entrant":{"id":9767558,"name":"Zapp","participants":[{"user":{"id":763240},"player":{"id":1207661,"gamerTag":"Zapp"}}]},"stats":{"score":{"value":2}}}},{"seed":{"placement":33,"seedNum":651},"standing":{"entrant":{"id":10094250,"name":"yeat | Kojer!","participants":[{"user":{"id":1846442},"player":{"id":2794621,"gamerTag":"Kojer!"}}]},"stats":{"score":{"value":0}}}}],"games":null}]}},"tourney_id":691230,"tourney_name":"Zapp","type":1}],[],[]]}}