{"name":"Degenerate-one-","id":837746,"alias":["Degenerate-one-"],"prefixi":["BXMB"],"location":{"state":"CA","country":"United States"},"smash":{"slug":"user/2f826779","url":"https://www.start.gg/user/2f826779"},"auth":[],"private":false,"images":[{"id":"2000570","type":"profile","url":"https://images.smash.gg/images/user/837746/image-189e250270e36419da22273cc387fd08.jpg","__typename":"Image"},{"id":"2000581","type":"banner","url":"https://images.smash.gg/images/user/837746/image-b1f0584fd16f2a8a1cc94020c38ae5d7.jpg","__typename":"Image"}],"tourneys":{"2017":[[],[],[]],"2018":[[],[],[]],"2019":[[{"data":{"main":{"wonAgainst":[{"name":"HahlSpacy","seed":675}],"loss":[{"id":3254296,"name":"767 | J4YB4R"},{"id":3462585,"name":"eggsoup"}],"lossPlacement":[257,385],"seed":862,"entity":3478901,"placement":513,"prizing":null},"sets":{"nodes":[{"createdAt":1564239974,"completedAt":1564244540,"startedAt":1564244243,"displayScore":"DQ","fullRoundText":"Losers Round 2","totalGames":5,"winnerId":3462585,"wPlacement":13,"lPlacement":17,"stream":null,"phaseGroup":{"displayIdentifier":"A30","phase":{"name":"Pools"}},"slots":[{"seed":{"placement":13,"seedNum":30},"standing":{"entrant":{"id":3462585,"name":"eggsoup","participants":[{"user":{"id":53975},"player":{"id":126745,"gamerTag":"eggsoup"}}]},"stats":{"score":{"value":-1}}}},{"seed":{"placement":17,"seedNum":862},"standing":{"entrant":{"id":3478901,"name":"BXMB | Degenerate-one-","participants":[{"user":{"id":837746},"player":{"id":1335135,"gamerTag":"Degenerate-one-"}}]},"stats":{"score":{"value":-1}}}}],"games":null},{"createdAt":1564239974,"completedAt":1564244178,"startedAt":1564243889,"displayScore":"DQ","fullRoundText":"Losers Round 1","totalGames":5,"winnerId":3478901,"wPlacement":17,"lPlacement":25,"stream":null,"phaseGroup":{"displayIdentifier":"A30","phase":{"name":"Pools"}},"slots":[{"seed":{"placement":17,"seedNum":862},"standing":{"entrant":{"id":3478901,"name":"BXMB | Degenerate-one-","participants":[{"user":{"id":837746},"player":{"id":1335135,"gamerTag":"Degenerate-one-"}}]},"stats":{"score":{"value":-1}}}},{"seed":{"placement":25,"seedNum":675},"standing":{"entrant":{"id":3444527,"name":"HahlSpacy","participants":[{"user":{"id":453872},"player":{"id":669775,"gamerTag":"HahlSpacy"}}]},"stats":{"score":{"value":-1}}}}],"games":null},{"createdAt":1564239974,"completedAt":1564243823,"startedAt":1564243235,"displayScore":"DQ","fullRoundText":"Winners Round 1","totalGames":5,"winnerId":3254296,"wPlacement":17,"lPlacement":25,"stream":null,"phaseGroup":{"displayIdentifier":"A30","phase":{"name":"Pools"}},"slots":[{"seed":{"placement":9,"seedNum":163},"standing":{"entrant":{"id":3254296,"name":"767 | J4YB4R","participants":[{"user":{"id":802162},"player":{"id":1272765,"gamerTag":"J4YB4R"}}]},"stats":{"score":{"value":-1}}}},{"seed":{"placement":17,"seedNum":862},"standing":{"entrant":{"id":3478901,"name":"BXMB | Degenerate-one-","participants":[{"user":{"id":837746},"player":{"id":1335135,"gamerTag":"Degenerate-one-"}}]},"stats":{"score":{"value":-1}}}}],"games":null}]}},"tourney_id":357407,"tourney_name":"Degenerate-one-","type":0},{"data":{"main":{"wonAgainst":[{"name":"HahlSpacy","seed":675}],"loss":[{"id":3254296,"name":"767 | J4YB4R"},{"id":3462585,"name":"eggsoup"}],"lossPlacement":[257,385],"seed":862,"entity":3478901,"placement":513,"prizing":null},"sets":{"nodes":[{"createdAt":1564239974,"completedAt":1564244540,"startedAt":1564244243,"displayScore":"DQ","fullRoundText":"Losers Round 2","totalGames":5,"winnerId":3462585,"wPlacement":13,"lPlacement":17,"stream":null,"phaseGroup":{"displayIdentifier":"A30","phase":{"name":"Pools"}},"slots":[{"seed":{"placement":13,"seedNum":30},"standing":{"entrant":{"id":3462585,"name":"eggsoup","participants":[{"user":{"id":53975},"player":{"id":126745,"gamerTag":"eggsoup"}}]},"stats":{"score":{"value":-1}}}},{"seed":{"placement":17,"seedNum":862},"standing":{"entrant":{"id":3478901,"name":"BXMB | Degenerate-one-","participants":[{"user":{"id":837746},"player":{"id":1335135,"gamerTag":"Degenerate-one-"}}]},"stats":{"score":{"value":-1}}}}],"games":null},{"createdAt":1564239974,"completedAt":1564244178,"startedAt":1564243889,"displayScore":"DQ","fullRoundText":"Losers Round 1","totalGames":5,"winnerId":3478901,"wPlacement":17,"lPlacement":25,"stream":null,"phaseGroup":{"displayIdentifier":"A30","phase":{"name":"Pools"}},"slots":[{"seed":{"placement":17,"seedNum":862},"standing":{"entrant":{"id":3478901,"name":"BXMB | Degenerate-one-","participants":[{"user":{"id":837746},"player":{"id":1335135,"gamerTag":"Degenerate-one-"}}]},"stats":{"score":{"value":-1}}}},{"seed":{"placement":25,"seedNum":675},"standing":{"entrant":{"id":3444527,"name":"HahlSpacy","participants":[{"user":{"id":453872},"player":{"id":669775,"gamerTag":"HahlSpacy"}}]},"stats":{"score":{"value":-1}}}}],"games":null},{"createdAt":1564239974,"completedAt":1564243823,"startedAt":1564243235,"displayScore":"DQ","fullRoundText":"Winners Round 1","totalGames":5,"winnerId":3254296,"wPlacement":17,"lPlacement":25,"stream":null,"phaseGroup":{"displayIdentifier":"A30","phase":{"name":"Pools"}},"slots":[{"seed":{"placement":9,"seedNum":163},"standing":{"entrant":{"id":3254296,"name":"767 | J4YB4R","participants":[{"user":{"id":802162},"player":{"id":1272765,"gamerTag":"J4YB4R"}}]},"stats":{"score":{"value":-1}}}},{"seed":{"placement":17,"seedNum":862},"standing":{"entrant":{"id":3478901,"name":"BXMB | Degenerate-one-","participants":[{"user":{"id":837746},"player":{"id":1335135,"gamerTag":"Degenerate-one-"}}]},"stats":{"score":{"value":-1}}}}],"games":null}]}},"tourney_id":357407,"tourney_name":"Degenerate-one-","type":1}],[],[]],"2020":[[{"data":{"main":{"wonAgainst":[],"loss":[{"id":5031221,"name":"chuyqwerty"},{"id":4942565,"name":"NJVS | Mikato"}],"lossPlacement":[33,1025],"seed":1604,"entity":4958296,"placement":2049,"prizing":null},"sets":{"nodes":[{"createdAt":1587836720,"completedAt":1587839000,"startedAt":1587838639,"displayScore":"DQ","fullRoundText":"Losers Round 2","totalGames":5,"winnerId":4942565,"wPlacement":49,"lPlacement":65,"stream":null,"phaseGroup":{"displayIdentifier":"A4","phase":{"name":"Bracket"}},"slots":[{"seed":{"placement":33,"seedNum":1277},"standing":{"entrant":{"id":4942565,"name":"NJVS | Mikato","participants":[{"user":{"id":171551},"player":{"id":266855,"gamerTag":"NJVS | Mikato"}}]},"stats":{"score":{"value":-1}}}},{"seed":{"placement":65,"seedNum":1604},"standing":{"entrant":{"id":4958296,"name":"BXMB | Degenerate-one-","participants":[{"user":{"id":837746},"player":{"id":1335135,"gamerTag":"Degenerate-one-"}}]},"stats":{"score":{"value":-1}}}}],"games":null},{"createdAt":1587836720,"completedAt":1587838266,"startedAt":1587837671,"displayScore":"DQ","fullRoundText":"Winners Round 1","totalGames":5,"winnerId":5031221,"wPlacement":65,"lPlacement":65,"stream":null,"phaseGroup":{"displayIdentifier":"A4","phase":{"name":"Bracket"}},"slots":[{"seed":{"placement":65,"seedNum":1604},"standing":{"entrant":{"id":4958296,"name":"BXMB | Degenerate-one-","participants":[{"user":{"id":837746},"player":{"id":1335135,"gamerTag":"Degenerate-one-"}}]},"stats":{"score":{"value":-1}}}},{"seed":{"placement":3,"seedNum":2493},"standing":{"entrant":{"id":5031221,"name":"chuyqwerty","participants":[{"user":{"id":179299},"player":{"id":276773,"gamerTag":"chuyqwerty"}}]},"stats":{"score":{"value":0}}}}],"games":null}]}},"tourney_id":457199,"tourney_name":"Degenerate-one-","type":0},{"data":{"main":{"wonAgainst":[{"name":"Dabyardigans","seed":276},{"name":"Wazzupluckyluke","seed":468},{"name":"zaawarrudo","seed":532},{"name":"A1Sali","seed":1005}],"loss":[{"id":4532297,"name":"RR | DoubleDime"},{"id":4692451,"name":"Goldson"}],"lossPlacement":[13,129],"seed":1044,"entity":4680941,"placement":257,"prizing":null},"sets":{"nodes":[{"createdAt":1582397306,"completedAt":1582403252,"startedAt":1582402803,"displayScore":"Goldson 2 - Degenerate-one- 0","fullRoundText":"Losers Round 5","totalGames":5,"winnerId":4692451,"wPlacement":7,"lPlacement":9,"stream":null,"phaseGroup":{"displayIdentifier":"A20","phase":{"name":"Pools"}},"slots":[{"seed":{"placement":5,"seedNum":1172},"standing":{"entrant":{"id":4692451,"name":"Goldson","participants":[{"user":{"id":491056},"player":{"id":735317,"gamerTag":"xris"}}]},"stats":{"score":{"value":2}}}},{"seed":{"placement":9,"seedNum":1044},"standing":{"entrant":{"id":4680941,"name":"Degenerate-one-","participants":[{"user":{"id":837746},"player":{"id":1335135,"gamerTag":"Degenerate-one-"}}]},"stats":{"score":{"value":0}}}}],"games":[{"winnerId":4692451,"stage":null,"selections":[{"selectionType":"CHARACTER","selectionValue":159,"entrant":{"name":"Goldson"}},{"selectionType":"CHARACTER","selectionValue":170,"entrant":{"name":"Degenerate-one-"}}]},{"winnerId":4692451,"stage":null,"selections":null}]},{"createdAt":1582397306,"completedAt":1582402732,"startedAt":1582401871,"displayScore":"Dabyardigans 1 - Degenerate-one- 2","fullRoundText":"Losers Round 4","totalGames":5,"winnerId":4680941,"wPlacement":9,"lPlacement":13,"stream":null,"phaseGroup":{"displayIdentifier":"A20","phase":{"name":"Pools"}},"slots":[{"seed":{"placement":13,"seedNum":276},"standing":{"entrant":{"id":4552040,"name":"Dabyardigans","participants":[{"user":{"id":1002139},"player":{"id":1636343,"gamerTag":"Dabyardigans"}}]},"stats":{"score":{"value":1}}}},{"seed":{"placement":9,"seedNum":1044},"standing":{"entrant":{"id":4680941,"name":"Degenerate-one-","participants":[{"user":{"id":837746},"player":{"id":1335135,"gamerTag":"Degenerate-one-"}}]},"stats":{"score":{"value":2}}}}],"games":[{"winnerId":4680941,"stage":null,"selections":[{"selectionType":"CHARACTER","selectionValue":1160,"entrant":{"name":"Dabyardigans"}},{"selectionType":"CHARACTER","selectionValue":170,"entrant":{"name":"Degenerate-one-"}}]},{"winnerId":4552040,"stage":null,"selections":[{"selectionType":"CHARACTER","selectionValue":1451,"entrant":{"name":"Dabyardigans"}}]},{"winnerId":4680941,"stage":null,"selections":[{"selectionType":"CHARACTER","selectionValue":170,"entrant":{"name":"Degenerate-one-"}}]}]},{"createdAt":1582397306,"completedAt":1582400594,"startedAt":1582400028,"displayScore":"Wazzupluckyluke 0 - Degenerate-one- 2","fullRoundText":"Losers Round 3","totalGames":5,"winnerId":4680941,"wPlacement":13,"lPlacement":17,"stream":null,"phaseGroup":{"displayIdentifier":"A20","phase":{"name":"Pools"}},"slots":[{"seed":{"placement":17,"seedNum":468},"standing":{"entrant":{"id":4594674,"name":"Wazzupluckyluke","participants":[{"user":{"id":802137},"player":{"id":1272728,"gamerTag":"D_0uble"}}]},"stats":{"score":{"value":0}}}},{"seed":{"placement":9,"seedNum":1044},"standing":{"entrant":{"id":4680941,"name":"Degenerate-one-","participants":[{"user":{"id":837746},"player":{"id":1335135,"gamerTag":"Degenerate-one-"}}]},"stats":{"score":{"value":2}}}}],"games":[{"winnerId":4680941,"stage":null,"selections":[{"selectionType":"CHARACTER","selectionValue":532,"entrant":{"name":"Wazzupluckyluke"}},{"selectionType":"CHARACTER","selectionValue":170,"entrant":{"name":"Degenerate-one-"}}]},{"winnerId":4680941,"stage":null,"selections":null}]},{"createdAt":1582397306,"completedAt":1582399936,"startedAt":1582399425,"displayScore":"zaawarrudo 0 - Degenerate-one- 2","fullRoundText":"Losers Round 2","totalGames":5,"winnerId":4680941,"wPlacement":17,"lPlacement":25,"stream":null,"phaseGroup":{"displayIdentifier":"A20","phase":{"name":"Pools"}},"slots":[{"seed":{"placement":25,"seedNum":532},"standing":{"entrant":{"id":4611867,"name":"zaawarrudo","participants":[{"user":{"id":1010515},"player":{"id":1651828,"gamerTag":"zaawarrudo"}}]},"stats":{"score":{"value":0}}}},{"seed":{"placement":9,"seedNum":1044},"standing":{"entrant":{"id":4680941,"name":"Degenerate-one-","participants":[{"user":{"id":837746},"player":{"id":1335135,"gamerTag":"Degenerate-one-"}}]},"stats":{"score":{"value":2}}}}],"games":[{"winnerId":4680941,"stage":null,"selections":[{"selectionType":"CHARACTER","selectionValue":171,"entrant":{"name":"zaawarrudo"}},{"selectionType":"CHARACTER","selectionValue":170,"entrant":{"name":"Degenerate-one-"}}]},{"winnerId":4680941,"stage":null,"selections":null}]},{"createdAt":1582397306,"completedAt":1582399297,"startedAt":1582398767,"displayScore":"RR | DoubleDime 2 - Degenerate-one- 0","fullRoundText":"Winners Round 2","totalGames":5,"winnerId":4532297,"wPlacement":17,"lPlacement":25,"stream":null,"phaseGroup":{"displayIdentifier":"A20","phase":{"name":"Pools"}},"slots":[{"seed":{"placement":3,"seedNum":20},"standing":{"entrant":{"id":4532297,"name":"RR | DoubleDime","participants":[{"user":{"id":230284},"player":{"id":338439,"gamerTag":"DoubleDime"}}]},"stats":{"score":{"value":2}}}},{"seed":{"placement":9,"seedNum":1044},"standing":{"entrant":{"id":4680941,"name":"Degenerate-one-","participants":[{"user":{"id":837746},"player":{"id":1335135,"gamerTag":"Degenerate-one-"}}]},"stats":{"score":{"value":0}}}}],"games":[{"winnerId":4532297,"stage":null,"selections":[{"selectionType":"CHARACTER","selectionValue":1161,"entrant":{"name":"RR | DoubleDime"}},{"selectionType":"CHARACTER","selectionValue":170,"entrant":{"name":"Degenerate-one-"}}]},{"winnerId":4532297,"stage":null,"selections":null}]},{"createdAt":1582397306,"completedAt":1582398654,"startedAt":1582398075,"displayScore":"DQ","fullRoundText":"Winners Round 1","totalGames":5,"winnerId":4680941,"wPlacement":25,"lPlacement":33,"stream":null,"phaseGroup":{"displayIdentifier":"A20","phase":{"name":"Pools"}},"slots":[{"seed":{"placement":33,"seedNum":1005},"standing":{"entrant":{"id":4675646,"name":"A1Sali","participants":[{"user":{"id":1020786},"player":{"id":1668785,"gamerTag":"A1Sali"}}]},"stats":{"score":{"value":-1}}}},{"seed":{"placement":9,"seedNum":1044},"standing":{"entrant":{"id":4680941,"name":"Degenerate-one-","participants":[{"user":{"id":837746},"player":{"id":1335135,"gamerTag":"Degenerate-one-"}}]},"stats":{"score":{"value":0}}}}],"games":null}]}},"tourney_id":440325,"tourney_name":"Degenerate-one-","type":0}],[{"data":{"main":{"wonAgainst":[],"loss":[{"id":5036732,"name":"Knife / HypxTicky"},{"id":5016963,"name":"LerkinMurkin / Usedbumbug11"}],"lossPlacement":[193,385],"seed":348,"entity":4958320,"placement":513,"prizing":null},"sets":{"nodes":[{"createdAt":1587236078,"completedAt":1587239844,"startedAt":1587239531,"displayScore":"DQ","fullRoundText":"Losers Round 2","totalGames":5,"winnerId":5016963,"wPlacement":49,"lPlacement":65,"stream":null,"phaseGroup":{"displayIdentifier":"C5","phase":{"name":"Bracket"}},"slots":[{"seed":{"placement":49,"seedNum":524},"standing":{"entrant":{"id":5016963,"name":"LerkinMurkin / Usedbumbug11","participants":[{"user":{"id":1077362},"player":{"id":1760967,"gamerTag":"Usedbumbug11"}},{"user":{"id":1077328},"player":{"id":1760927,"gamerTag":"LerkinMurkin"}}]},"stats":{"score":{"value":-1}}}},{"seed":{"placement":65,"seedNum":348},"standing":{"entrant":{"id":4958320,"name":"Degenerate-one- / XenonVerse-","participants":[{"user":{"id":837746},"player":{"id":1335135,"gamerTag":"Degenerate-one-"}},{"user":{"id":1065313},"player":{"id":1739850,"gamerTag":"XenonVerse-"}}]},"stats":{"score":{"value":-1}}}}],"games":null},{"createdAt":1587236078,"completedAt":1587238820,"startedAt":1587238258,"displayScore":"DQ","fullRoundText":"Winners Round 1","totalGames":5,"winnerId":5036732,"wPlacement":65,"lPlacement":65,"stream":null,"phaseGroup":{"displayIdentifier":"C5","phase":{"name":"Bracket"}},"slots":[{"seed":{"placement":65,"seedNum":348},"standing":{"entrant":{"id":4958320,"name":"Degenerate-one- / XenonVerse-","participants":[{"user":{"id":837746},"player":{"id":1335135,"gamerTag":"Degenerate-one-"}},{"user":{"id":1065313},"player":{"id":1739850,"gamerTag":"XenonVerse-"}}]},"stats":{"score":{"value":-1}}}},{"seed":{"placement":25,"seedNum":677},"standing":{"entrant":{"id":5036732,"name":"Knife / HypxTicky","participants":[{"user":{"id":913951},"player":{"id":1462139,"gamerTag":"Kniife"}},{"user":{"id":1061152},"player":{"id":1734268,"gamerTag":"HypxTicky"}}]},"stats":{"score":{"value":0}}}}],"games":null}]}},"tourney_id":457200,"type":0,"tourney_name":"Degenerate-one-","team":{"teamname":"Degenerate-one- / XenonVerse-","teammate":{"id":1065313,"private":false,"name":"XenonVerse-","user":{"smash_id":1065313,"images":[],"url":"https://www.start.gg/user/41f17895","playerSlug":"user/41f17895"}}}},{"data":{"main":{"wonAgainst":[{"name":"RyXin / High","seed":277},{"name":"GoldJaguarYT / KidFlashFast","seed":325}],"loss":[{"id":4713434,"name":"Sabrecop / SlipRee"},{"id":4585046,"name":"Linguini / Silverarrow360"}],"lossPlacement":[65,49],"seed":236,"entity":4681066,"placement":193,"prizing":null},"sets":{"nodes":[{"createdAt":1583001969,"completedAt":1583006120,"startedAt":1583005591,"displayScore":"Linguini / Silverarrow360 2 - Degenerate-one- / ANBU_HITTER 0","fullRoundText":"Losers Round 2","totalGames":5,"winnerId":4585046,"wPlacement":17,"lPlacement":25,"stream":null,"phaseGroup":{"displayIdentifier":"B5","phase":{"name":"Pools"}},"slots":[{"seed":{"placement":7,"seedNum":108},"standing":{"entrant":{"id":4585046,"name":"Linguini / Silverarrow360","participants":[{"user":{"id":954403},"player":{"id":1542778,"gamerTag":"Linguini"}},{"user":{"id":866805},"player":{"id":1386099,"gamerTag":"Silverarrow360"}}]},"stats":{"score":{"value":2}}}},{"seed":{"placement":25,"seedNum":236},"standing":{"entrant":{"id":4681066,"name":"Degenerate-one- / ANBU_HITTER","participants":[{"user":{"id":837746},"player":{"id":1335135,"gamerTag":"Degenerate-one-"}},{"user":{"id":1021672},"player":{"id":1670171,"gamerTag":"ANBU_HITTER"}}]},"stats":{"score":{"value":0}}}}],"games":[{"winnerId":4585046,"stage":null,"selections":null},{"winnerId":4585046,"stage":null,"selections":null}]},{"createdAt":1583001969,"completedAt":1583004282,"startedAt":1583003802,"displayScore":"Degenerate-one- / ANBU_HITTER 2 - GoldJaguarYT / KidFlashFast 0","fullRoundText":"Losers Round 1","totalGames":5,"winnerId":4681066,"wPlacement":25,"lPlacement":33,"stream":null,"phaseGroup":{"displayIdentifier":"B5","phase":{"name":"Pools"}},"slots":[{"seed":{"placement":25,"seedNum":236},"standing":{"entrant":{"id":4681066,"name":"Degenerate-one- / ANBU_HITTER","participants":[{"user":{"id":837746},"player":{"id":1335135,"gamerTag":"Degenerate-one-"}},{"user":{"id":1021672},"player":{"id":1670171,"gamerTag":"ANBU_HITTER"}}]},"stats":{"score":{"value":2}}}},{"seed":{"placement":33,"seedNum":325},"standing":{"entrant":{"id":4715229,"name":"GoldJaguarYT / KidFlashFast","participants":[{"user":{"id":1011582},"player":{"id":1653701,"gamerTag":"GoldJaguarYT"}},{"user":{"id":1027315},"player":{"id":1679872,"gamerTag":"KidFlashFast"}}]},"stats":{"score":{"value":0}}}}],"games":[{"winnerId":4681066,"stage":null,"selections":null},{"winnerId":4681066,"stage":null,"selections":null}]},{"createdAt":1583001969,"completedAt":1583003749,"startedAt":1583003298,"displayScore":"Sabrecop / SlipRee 2 - Degenerate-one- / ANBU_HITTER 0","fullRoundText":"Winners Round 2","totalGames":5,"winnerId":4713434,"wPlacement":17,"lPlacement":33,"stream":null,"phaseGroup":{"displayIdentifier":"B5","phase":{"name":"Pools"}},"slots":[{"seed":{"placement":9,"seedNum":21},"standing":{"entrant":{"id":4713434,"name":"Sabrecop / SlipRee","participants":[{"user":{"id":594840},"player":{"id":933067,"gamerTag":"Sabrecop"}},{"user":{"id":233300},"player":{"id":342828,"gamerTag":"SlipRee"}}]},"stats":{"score":{"value":2}}}},{"seed":{"placement":25,"seedNum":236},"standing":{"entrant":{"id":4681066,"name":"Degenerate-one- / ANBU_HITTER","participants":[{"user":{"id":837746},"player":{"id":1335135,"gamerTag":"Degenerate-one-"}},{"user":{"id":1021672},"player":{"id":1670171,"gamerTag":"ANBU_HITTER"}}]},"stats":{"score":{"value":0}}}}],"games":[{"winnerId":4713434,"stage":null,"selections":null},{"winnerId":4713434,"stage":null,"selections":null}]},{"createdAt":1583001969,"completedAt":1583003166,"startedAt":1583002485,"displayScore":"DQ","fullRoundText":"Winners Round 1","totalGames":5,"winnerId":4681066,"wPlacement":33,"lPlacement":33,"stream":null,"phaseGroup":{"displayIdentifier":"B5","phase":{"name":"Pools"}},"slots":[{"seed":{"placement":25,"seedNum":236},"standing":{"entrant":{"id":4681066,"name":"Degenerate-one- / ANBU_HITTER","participants":[{"user":{"id":837746},"player":{"id":1335135,"gamerTag":"Degenerate-one-"}},{"user":{"id":1021672},"player":{"id":1670171,"gamerTag":"ANBU_HITTER"}}]},"stats":{"score":{"value":0}}}},{"seed":{"placement":9,"seedNum":277},"standing":{"entrant":{"id":4703821,"name":"RyXin / High","participants":[{"user":{"id":416386},"player":{"id":595633,"gamerTag":"RyXin"}},{"user":{"id":420109},"player":{"id":600101,"gamerTag":"High"}}]},"stats":{"score":{"value":-1}}}}],"games":null}]}},"tourney_id":440326,"type":0,"tourney_name":"Degenerate-one-","team":{"teamname":"Degenerate-one- / ANBU_HITTER","teammate":{"id":1021672,"private":false,"name":"ANBU_HITTER","user":{"smash_id":1021672,"images":[],"url":"https://www.start.gg/user/c62d2412","playerSlug":"user/c62d2412"}}}},{"data":{"main":{"wonAgainst":[{"name":"Darkbot / Jet_Stream","seed":308},{"name":"jay_swing / HustleX_Frost","seed":756},{"name":"Bacon 918 / Hepzr","seed":1933}],"loss":[{"id":5627488,"name":"Reznik / wc"},{"id":5694772,"name":"Blocknot88 / R3D_D0T"}],"lossPlacement":[513,513],"seed":1332,"entity":5669091,"placement":769,"prizing":0},"sets":{"nodes":[{"createdAt":1595699928,"completedAt":1595705688,"startedAt":1595704924,"displayScore":"Degenerate-one- / XenonVerse- 0 - Blocknot88 / R3D_D0T 2","fullRoundText":"Losers Round 4","totalGames":5,"winnerId":5694772,"wPlacement":17,"lPlacement":25,"stream":null,"phaseGroup":{"displayIdentifier":"K5","phase":{"name":"Bracket"}},"slots":[{"seed":{"placement":25,"seedNum":1332},"standing":{"entrant":{"id":5669091,"name":"Degenerate-one- / XenonVerse-","participants":[{"user":{"id":837746},"player":{"id":1335135,"gamerTag":"Degenerate-one-"}},{"user":{"id":1065313},"player":{"id":1739850,"gamerTag":"XenonVerse-"}}]},"stats":{"score":{"value":0}}}},{"seed":{"placement":17,"seedNum":2253},"standing":{"entrant":{"id":5694772,"name":"Blocknot88 / R3D_D0T","participants":[{"user":{"id":790345},"player":{"id":1253022,"gamerTag":"Blocknot88"}},{"user":{"id":1238610},"player":{"id":1955050,"gamerTag":"R3D_D0T"}}]},"stats":{"score":{"value":2}}}}],"games":[{"winnerId":5694772,"stage":null,"selections":null},{"winnerId":5694772,"stage":null,"selections":null}]},{"createdAt":1595699928,"completedAt":1595703435,"startedAt":1595703067,"displayScore":"DQ","fullRoundText":"Losers Round 3","totalGames":5,"winnerId":5669091,"wPlacement":25,"lPlacement":33,"stream":null,"phaseGroup":{"displayIdentifier":"K5","phase":{"name":"Bracket"}},"slots":[{"seed":{"placement":33,"seedNum":756},"standing":{"entrant":{"id":5629858,"name":"jay_swing / HustleX_Frost","participants":[{"user":{"id":1217905},"player":{"id":1931542,"gamerTag":"jay_swing"}},{"user":{"id":1222628},"player":{"id":1936785,"gamerTag":"HustleX_Frost"}}]},"stats":{"score":{"value":-1}}}},{"seed":{"placement":25,"seedNum":1332},"standing":{"entrant":{"id":5669091,"name":"Degenerate-one- / XenonVerse-","participants":[{"user":{"id":837746},"player":{"id":1335135,"gamerTag":"Degenerate-one-"}},{"user":{"id":1065313},"player":{"id":1739850,"gamerTag":"XenonVerse-"}}]},"stats":{"score":{"value":0}}}}],"games":null},{"createdAt":1595699928,"completedAt":1595703014,"startedAt":1595702703,"displayScore":"DQ","fullRoundText":"Losers Round 2","totalGames":5,"winnerId":5669091,"wPlacement":33,"lPlacement":49,"stream":null,"phaseGroup":{"displayIdentifier":"K5","phase":{"name":"Bracket"}},"slots":[{"seed":{"placement":25,"seedNum":1332},"standing":{"entrant":{"id":5669091,"name":"Degenerate-one- / XenonVerse-","participants":[{"user":{"id":837746},"player":{"id":1335135,"gamerTag":"Degenerate-one-"}},{"user":{"id":1065313},"player":{"id":1739850,"gamerTag":"XenonVerse-"}}]},"stats":{"score":{"value":0}}}},{"seed":{"placement":49,"seedNum":308},"standing":{"entrant":{"id":5557970,"name":"Darkbot / Jet_Stream","participants":[{"user":{"id":1093559},"player":{"id":1780387,"gamerTag":"Darkbot"}},{"user":{"id":1049979},"player":{"id":1718551,"gamerTag":"Jet_Stream1"}}]},"stats":{"score":{"value":-1}}}}],"games":null},{"createdAt":1595699928,"completedAt":1595702596,"startedAt":1595701798,"displayScore":"Degenerate-one- / XenonVerse- 2 - Bacon 918 / Hepzr 0","fullRoundText":"Losers Round 1","totalGames":5,"winnerId":5669091,"wPlacement":49,"lPlacement":65,"stream":null,"phaseGroup":{"displayIdentifier":"K5","phase":{"name":"Bracket"}},"slots":[{"seed":{"placement":25,"seedNum":1332},"standing":{"entrant":{"id":5669091,"name":"Degenerate-one- / XenonVerse-","participants":[{"user":{"id":837746},"player":{"id":1335135,"gamerTag":"Degenerate-one-"}},{"user":{"id":1065313},"player":{"id":1739850,"gamerTag":"XenonVerse-"}}]},"stats":{"score":{"value":2}}}},{"seed":{"placement":65,"seedNum":1933},"standing":{"entrant":{"id":5685740,"name":"Bacon 918 / Hepzr","participants":[{"user":{"id":1228949},"player":{"id":1943952,"gamerTag":"Bacon 918"}},{"user":{"id":1169084},"player":{"id":1872335,"gamerTag":"Hepzr"}}]},"stats":{"score":{"value":0}}}}],"games":[{"winnerId":5669091,"stage":null,"selections":null},{"winnerId":5669091,"stage":null,"selections":null}]},{"createdAt":1595699928,"completedAt":1595701651,"startedAt":1595700927,"displayScore":"Reznik / wc 2 - Degenerate-one- / XenonVerse- 0","fullRoundText":"Winners Round 2","totalGames":5,"winnerId":5627488,"wPlacement":33,"lPlacement":65,"stream":null,"phaseGroup":{"displayIdentifier":"K5","phase":{"name":"Bracket"}},"slots":[{"seed":{"placement":17,"seedNum":717},"standing":{"entrant":{"id":5627488,"name":"Reznik / wc","participants":[{"user":{"id":1062364},"player":{"id":1735993,"gamerTag":"walker"}},{"user":{"id":1082970},"player":{"id":1768642,"gamerTag":"RezniK"}}]},"stats":{"score":{"value":2}}}},{"seed":{"placement":25,"seedNum":1332},"standing":{"entrant":{"id":5669091,"name":"Degenerate-one- / XenonVerse-","participants":[{"user":{"id":837746},"player":{"id":1335135,"gamerTag":"Degenerate-one-"}},{"user":{"id":1065313},"player":{"id":1739850,"gamerTag":"XenonVerse-"}}]},"stats":{"score":{"value":0}}}}],"games":[{"winnerId":5627488,"stage":null,"selections":null},{"winnerId":5627488,"stage":null,"selections":null}]}]}},"tourney_id":471345,"type":0,"tourney_name":"Degenerate-one-","team":{"teamname":"Degenerate-one- / XenonVerse-","teammate":{"id":1065313,"private":false,"name":"XenonVerse-","user":{"smash_id":1065313,"images":[],"url":"https://www.start.gg/user/41f17895","playerSlug":"user/41f17895"}}}},{"data":{"main":{"wonAgainst":[],"loss":[{"id":5492726,"name":"Shadow0q12 / UNSTOPABLExGOD"},{"id":5484702,"name":"MrButterVenom / allToast"}],"lossPlacement":[65,257],"seed":989,"entity":5535800,"placement":769,"prizing":null},"sets":{"nodes":[{"createdAt":1593280007,"completedAt":1593282086,"startedAt":1593281768,"displayScore":"DQ","fullRoundText":"Losers Round 2","totalGames":5,"winnerId":5484702,"wPlacement":33,"lPlacement":49,"stream":null,"phaseGroup":{"displayIdentifier":"E4","phase":{"name":"Bracket"}},"slots":[{"seed":{"placement":17,"seedNum":477},"standing":{"entrant":{"id":5484702,"name":"MrButterVenom / allToast","participants":[{"user":{"id":233119},"player":{"id":342644,"gamerTag":"Luzinity"}},{"user":{"id":233122},"player":{"id":342646,"gamerTag":"allToast"}}]},"stats":{"score":{"value":0}}}},{"seed":{"placement":49,"seedNum":989},"standing":{"entrant":{"id":5535800,"name":"Degenerate-one- / XenonVerse-","participants":[{"user":{"id":837746},"player":{"id":1335135,"gamerTag":"Degenerate-one-"}},{"user":{"id":1065313},"player":{"id":1739850,"gamerTag":"XenonVerse-"}}]},"stats":{"score":{"value":-1}}}}],"games":null},{"createdAt":1593280007,"completedAt":1593281481,"startedAt":1593280894,"displayScore":"DQ","fullRoundText":"Winners Round 2","totalGames":5,"winnerId":5492726,"wPlacement":33,"lPlacement":49,"stream":null,"phaseGroup":{"displayIdentifier":"E4","phase":{"name":"Bracket"}},"slots":[{"seed":{"placement":5,"seedNum":36},"standing":{"entrant":{"id":5492726,"name":"Shadow0q12 / UNSTOPABLExGOD","participants":[{"user":{"id":879411},"player":{"id":1405338,"gamerTag":"Shadow0q12"}},{"user":{"id":874248},"player":{"id":1396711,"gamerTag":"UNSTOPABLExGOD"}}]},"stats":{"score":{"value":0}}}},{"seed":{"placement":49,"seedNum":989},"standing":{"entrant":{"id":5535800,"name":"Degenerate-one- / XenonVerse-","participants":[{"user":{"id":837746},"player":{"id":1335135,"gamerTag":"Degenerate-one-"}},{"user":{"id":1065313},"player":{"id":1739850,"gamerTag":"XenonVerse-"}}]},"stats":{"score":{"value":-1}}}}],"games":null}]}},"tourney_id":482767,"type":0,"tourney_name":"Degenerate-one-","team":{"teamname":"Degenerate-one- / XenonVerse-","teammate":{"id":1065313,"private":false,"name":"XenonVerse-","user":{"smash_id":1065313,"images":[],"url":"https://www.start.gg/user/41f17895","playerSlug":"user/41f17895"}}}}],[]],"2021":[[],[],[]],"2022":[[],[],[]]}}